{"parts":[{"ytid":"AoqJGcSqGaA","start":0,"length":38599.951,"timestamp":1489183295,"info":[],"muted":[[33600,34080]],"unmuted":[],"discontinuity":[],"contentid_removed":[],"contentid_matched":[],"editions":[],"state":"uploaded"}],"title":"Deadmau5","game":"Creative","timestamp":1489183295,"length":38599,"formattedTime":{"date_str":"10 Mar 2017","time_str":"17:01","tz_str":"EST"},"formattedTimeUTC":{"date_str":"10 Mar 2017","time_str":"22:01"},"isTimeApprox":false,"type":"twitch","originalAvailable":true,"streamNumber":203,"hlsUrls":{"1080p60":"https:\/\/vod-secure.twitch.tv\/c3dc6409b9_deadmau5_24749596896_615520305\/chunked\/index-muted-K74T185HOL.m3u8","audio_only":"https:\/\/vod-secure.twitch.tv\/c3dc6409b9_deadmau5_24749596896_615520305\/audio_only\/index-muted-K74T185HOL.m3u8","720p":"https:\/\/vod-secure.twitch.tv\/c3dc6409b9_deadmau5_24749596896_615520305\/high\/index-muted-K74T185HOL.m3u8","360p":"https:\/\/vod-secure.twitch.tv\/c3dc6409b9_deadmau5_24749596896_615520305\/low\/index-muted-K74T185HOL.m3u8","480p":"https:\/\/vod-secure.twitch.tv\/c3dc6409b9_deadmau5_24749596896_615520305\/medium\/index-muted-K74T185HOL.m3u8","226p":"https:\/\/vod-secure.twitch.tv\/c3dc6409b9_deadmau5_24749596896_615520305\/mobile\/index-muted-K74T185HOL.m3u8"},"vsig":"eyJ2IjoiMTI3NzcyMTY3IiwicCI6WzM4NjAxXX0=:197673d6adedac8e2c331ef130c63f7d","hasChat":true}