{"parts":[{"ytid":"HIHHNeJVDio","start":0,"length":1395,"timestamp":1599990342,"info":[],"contentid_removed":[],"contentid_matched":[],"editions":{},"state":"uploaded"}],"timestamp":1599990342,"length":1395,"formattedTime":{"date_str":"13 Sep 2020","time_str":"05:45","tz_str":"EDT"},"formattedTimeUTC":{"date_str":"13 Sep 2020","time_str":"09:45"},"isTimeApprox":false,"type":"mau5trap.tv","originalAvailable":false,"vsig":"eyJ2IjoiMTU5OTk5MDM0MiIsInAiOlsxMzk3XX0=:032aacf7a908ff69d8efda97322307fa","hasChat":false,"infoTags":[],"id":"1599990342"}