{"parts":[{"ytid":"pcFwj4BZ41c","start":0,"length":6005,"timestamp":1599561781,"info":[],"contentid_removed":[],"contentid_matched":[],"editions":{},"state":"uploaded"}],"timestamp":1599561781,"length":6005,"formattedTime":{"date_str":"8 Sep 2020","time_str":"06:43","tz_str":"EDT"},"formattedTimeUTC":{"date_str":"8 Sep 2020","time_str":"10:43"},"isTimeApprox":false,"type":"mau5trap.tv","originalAvailable":false,"vsig":"eyJ2IjoiMTU5OTU2MTc4MSIsInAiOls2MDA3XX0=:efa9598f93673b3c2c0198f11a4ebe2c","hasChat":false,"infoTags":[],"id":"1599561781"}