{"parts":[{"ytid":null,"start":0,"length":1593,"timestamp":1604384211,"info":[],"contentid_removed":[],"contentid_matched":[{"t":[10,262],"title":"Falling Down (Live 2007)","artist":"The Birthday Massacre","label":"Metropolis Records"},{"t":[265,546],"title":"Greenways Trajectory","artist":"Squarepusher","label":"Warp"},{"t":[1110,1346],"title":"Never Catch Me (feat. Kendrick Lamar)","artist":"Flying Lotus","label":"Warp Records"},{"t":[1428,1507],"title":"In the Annexe","artist":"Boards of Canada","label":"Warp"}],"editions":{},"state":"access_restricted","access_control":{"video_id":"1604384211:1665999441"}}],"timestamp":1604384211,"length":1593,"formattedTime":{"date_str":"3 Nov 2020","time_str":"01:16","tz_str":"EST"},"formattedTimeUTC":{"date_str":"3 Nov 2020","time_str":"06:16"},"isTimeApprox":false,"type":"mau5trap.tv","originalAvailable":false,"vsig":"eyJ2IjoiMTYwNDM4NDIxMSIsInAiOlsxNTk1XX0=:c7c190614bf92d6f4a9fc76e7bed4b89","hasChat":false,"infoTags":["lock"],"id":"1604384211"}