{"parts":[{"ytid":null,"start":0,"length":17585,"timestamp":1660630386,"info":[],"contentid_removed":[],"contentid_matched":[],"editions":{},"state":"access_restricted","access_control":{"video_id":"2022-08-16_08-13-06:1661436747"}}],"timestamp":1660630386,"length":17585,"formattedTime":{"date_str":"16 Aug 2022","time_str":"02:13","tz_str":"EDT"},"formattedTimeUTC":{"date_str":"16 Aug 2022","time_str":"06:13"},"isTimeApprox":false,"type":"twitch","originalAvailable":false,"vsig":"eyJ2IjoiMjAyMi0wOC0xNl8wOC0xMy0wNiIsInAiOlsxNzU4N119:50e31a61cad4986986a5c0a0ceff5826","hasChat":false,"infoTags":["lock"],"id":"2022-08-16_08-13-06","title":"Oberhasli content pipeline yay","game":"Software and Game Development"}