{"parts":[{"ytid":null,"start":0,"length":28933,"timestamp":1652083989,"info":[],"contentid_removed":[],"contentid_matched":[],"editions":{},"state":"access_restricted","access_control":{"video_id":"2022-05-09_08-47-09/1:1652186203"}},{"ytid":null,"start":28933,"length":28934,"timestamp":1652112922,"info":[],"contentid_removed":[],"contentid_matched":[],"editions":{},"state":"access_restricted","access_control":{"video_id":"2022-05-09_08-47-09/2:1652186203"}},{"ytid":null,"start":57867,"length":28934,"timestamp":1652141856,"info":[],"contentid_removed":[],"contentid_matched":[],"editions":{},"state":"access_restricted","access_control":{"video_id":"2022-05-09_08-47-09/3:1652186203"}}],"timestamp":1652083989,"length":86801,"formattedTime":{"date_str":"9 May 2022","time_str":"04:13","tz_str":"EDT"},"formattedTimeUTC":{"date_str":"9 May 2022","time_str":"08:13"},"isTimeApprox":false,"type":"twitch","originalAvailable":false,"vsig":"eyJ2IjoiMjAyMi0wNS0wOV8wOC00Ny0wOSIsInAiOlsyODkzNSwyODkzNiwyODkzNl19:d6e5a8d9c880f536e56641d4c67e4709","hasChat":false,"infoTags":["lock"],"id":"2022-05-09_08-47-09","title":"meowingtons simulator (v1.0)","game":"Software and Game Development"}