{"parts":[{"ytid":"C73uOjIMLFM","start":0,"length":16418.311,"timestamp":1520554674,"info":[],"muted":[],"unmuted":[],"discontinuity":[],"contentid_removed":[],"contentid_matched":[],"editions":[],"state":"uploaded"}],"title":"deadmau5 n stuff","game":"PLAYERUNKNOWN'S BATTLEGROUNDS","timestamp":1520554674,"length":16418,"formattedTime":{"date_str":"8 Mar 2018","time_str":"19:17","tz_str":"EST"},"formattedTimeUTC":{"date_str":"9 Mar 2018","time_str":"00:17"},"isTimeApprox":false,"type":"twitch","originalAvailable":true,"streamNumber":500,"hlsUrls":{"1080p60":"https:\/\/vod-secure.twitch.tv\/99cba4cf8b4f59ad8385_deadmau5_27861803296_810032870\/chunked\/index-dvr.m3u8","720p60":"https:\/\/vod-secure.twitch.tv\/99cba4cf8b4f59ad8385_deadmau5_27861803296_810032870\/720p60\/index-dvr.m3u8","720p":"https:\/\/vod-secure.twitch.tv\/99cba4cf8b4f59ad8385_deadmau5_27861803296_810032870\/720p30\/index-dvr.m3u8","480p":"https:\/\/vod-secure.twitch.tv\/99cba4cf8b4f59ad8385_deadmau5_27861803296_810032870\/480p30\/index-dvr.m3u8","Audio Only":"https:\/\/vod-secure.twitch.tv\/99cba4cf8b4f59ad8385_deadmau5_27861803296_810032870\/audio_only\/index-dvr.m3u8","360p":"https:\/\/vod-secure.twitch.tv\/99cba4cf8b4f59ad8385_deadmau5_27861803296_810032870\/360p30\/index-dvr.m3u8","160p":"https:\/\/vod-secure.twitch.tv\/99cba4cf8b4f59ad8385_deadmau5_27861803296_810032870\/160p30\/index-dvr.m3u8"},"vsig":"eyJ2IjoiMjM2Njg5MTM2IiwicCI6WzE2NDIwXX0=:e21d0f00008628afa47a6da753b073e6","hasChat":true}