{"parts":[{"ytid":"v3rlEkExSXc","start":0,"length":7625.535,"timestamp":1526403295,"info":[],"muted":[],"unmuted":[],"discontinuity":[],"contentid_removed":[],"contentid_matched":[],"editions":[],"state":"uploaded"}],"title":"deadmau5 n stuff","game":"PLAYERUNKNOWN'S BATTLEGROUNDS","timestamp":1526403295,"length":7625,"formattedTime":{"date_str":"15 May 2018","time_str":"12:54","tz_str":"EDT"},"formattedTimeUTC":{"date_str":"15 May 2018","time_str":"16:54"},"isTimeApprox":false,"type":"twitch","originalAvailable":true,"streamNumber":560,"hlsUrls":{"1080p60":"https:\/\/vod-secure.twitch.tv\/956794f01e0b5a995a69_deadmau5_28707646944_862898098\/chunked\/index-dvr.m3u8","720p60":"https:\/\/vod-secure.twitch.tv\/956794f01e0b5a995a69_deadmau5_28707646944_862898098\/720p60\/index-dvr.m3u8","720p":"https:\/\/vod-secure.twitch.tv\/956794f01e0b5a995a69_deadmau5_28707646944_862898098\/720p30\/index-dvr.m3u8","480p":"https:\/\/vod-secure.twitch.tv\/956794f01e0b5a995a69_deadmau5_28707646944_862898098\/480p30\/index-dvr.m3u8","Audio Only":"https:\/\/vod-secure.twitch.tv\/956794f01e0b5a995a69_deadmau5_28707646944_862898098\/audio_only\/index-dvr.m3u8","360p":"https:\/\/vod-secure.twitch.tv\/956794f01e0b5a995a69_deadmau5_28707646944_862898098\/360p30\/index-dvr.m3u8","160p":"https:\/\/vod-secure.twitch.tv\/956794f01e0b5a995a69_deadmau5_28707646944_862898098\/160p30\/index-dvr.m3u8"},"vsig":"eyJ2IjoiMjYxNjg0ODg0IiwicCI6Wzc2MjddfQ==:b1f92f52e10bed523be96991314bb13b","hasChat":true}