{"providers":[{"type":"youtube","displayName":"YouTube","providerData":{"parts":[{"ytid":"Wil-tEJ07i8","start":0,"length":20749,"timestamp":1529496711,"info":[],"contentid_removed":[],"contentid_matched":[{"t":[10815,11146],"title":"Drama Free (Extended Instrumental)","artist":"deadmau5","label":"mau5trap Recordings Limited"},{"t":[11304,11381],"title":"Nyquist","artist":"deadmau5","label":"mau5trap Recordings Limited"},{"t":[11383,11586],"title":"Glivch","artist":"deadmau5","label":"mau5trap Recordings Limited"},{"t":[11582,11918],"title":"10.8","artist":"deadmau5, Mr. Bill","label":"mau5trap Recordings Limited"},{"t":[11923,11967],"title":"Polyphobia","artist":"deadmau5","label":"mau5trap Recordings Limited"},{"t":[11978,12301],"title":"GG","artist":"deadmau5","label":"mau5trap Recordings Limited"},{"t":[12364,12596],"title":"ASEED","artist":"deadmau5","label":"mau5trap venture limited"}],"editions":{},"state":"uploaded"}]}}],"timestamp":1529496711,"length":20749,"formattedTime":{"date_str":"20 Jun 2018","time_str":"08:11","tz_str":"EDT"},"formattedTimeUTC":{"date_str":"20 Jun 2018","time_str":"12:11"},"isTimeApprox":false,"type":"twitch","originalAvailable":true,"vsig":"eyJ2IjoiMjc1NDA5MzA0IiwibCI6MjA3NTB9:e264e2a7072d44414c08860480c8f688","hasChat":true,"infoTags":[],"id":"275409304","title":"deadmau5 n stuff","game":"Creative","streamNumber":615,"hlsUrls":{"1080p60":"https://vod-secure.twitch.tv/c030d881caffaaf6db01_deadmau5_29162174064_891306042/chunked/index-dvr.m3u8","720p60":"https://vod-secure.twitch.tv/c030d881caffaaf6db01_deadmau5_29162174064_891306042/720p60/index-dvr.m3u8","720p":"https://vod-secure.twitch.tv/c030d881caffaaf6db01_deadmau5_29162174064_891306042/720p30/index-dvr.m3u8","480p":"https://vod-secure.twitch.tv/c030d881caffaaf6db01_deadmau5_29162174064_891306042/480p30/index-dvr.m3u8","Audio Only":"https://vod-secure.twitch.tv/c030d881caffaaf6db01_deadmau5_29162174064_891306042/audio_only/index-dvr.m3u8","360p":"https://vod-secure.twitch.tv/c030d881caffaaf6db01_deadmau5_29162174064_891306042/360p30/index-dvr.m3u8","160p":"https://vod-secure.twitch.tv/c030d881caffaaf6db01_deadmau5_29162174064_891306042/160p30/index-dvr.m3u8"}}