{"parts":[{"ytid":"I72pn3jDaTQ","start":0,"length":11633,"timestamp":1587179101,"info":[],"contentid_removed":[{"t":[1420,1763],"title":"Arcadia (unreleased)","artist":"deadmau5","label":"mau5trap Recordings Ltd"},{"t":[1818,1868],"title":"white feather (unreleased)","artist":"deadmau5","label":"mau5trap Recordings"},{"t":[2098,2127],"title":"white feather (unreleased)","artist":"deadmau5","label":"mau5trap Recordings"},{"t":[3649,3687],"title":"Omnifck (unreleased)","artist":"deadmau5","label":"mau5trap Recordings Ltd"},{"t":[3697,3734],"title":"Omnifck (unreleased)","artist":"deadmau5","label":"mau5trap Recordings Ltd"},{"t":[3797,3823],"title":"Omnifck (unreleased)","artist":"deadmau5","label":"mau5trap Recordings Ltd"},{"t":[11140,11431],"title":"Arcadia (unreleased)","artist":"deadmau5","label":"mau5trap Recordings Ltd"}],"contentid_matched":[{"t":[8826,8865],"title":"When The Summer Dies (Alternative Mix)","artist":"deadmau5 & Lights","label":"mau5trap Recordings Ltd"},{"t":[9462,9499],"title":"When The Summer Dies (Alternative Mix)","artist":"deadmau5 & Lights","label":"mau5trap Recordings Ltd"},{"t":[9605,9647],"title":"When The Summer Dies (Alternative Mix)","artist":"deadmau5 & Lights","label":"mau5trap Recordings Ltd"}],"editions":[],"state":"uploaded"}],"title":"Cube things","game":"Music","timestamp":1587179101,"length":11633,"formattedTime":{"date_str":"17 Apr 2020","time_str":"23:05","tz_str":"EDT"},"formattedTimeUTC":{"date_str":"18 Apr 2020","time_str":"03:05"},"isTimeApprox":false,"type":"mixer","originalAvailable":false,"streamNumber":105,"vsig":"eyJ2IjoiTjBrN2hXS1Q0RUNNX3JNdmxLVGIyUSIsInAiOlsxMTYzNV19:bb14dc2a4436eee75dcd3477e6278e99","hasChat":true}